{
    "/foobar/{:id}": {
        "page": "foobar.handlebars",
        "query": [
            {
                "collectionName": "portfolios",
                "query": {
                    "projectPK": "9c8cee60-61fe-11e9-b3ed-15bcaf8bd110"
                }
            }
        ]
    },
    "/foobar": {
        "params": {
            "title": "FUBAR"
        },
        "page": "foobar.handlebars"
    },
    "/$": {
        "params": {
            "title": "Home sweet home"
        },
        "page": "home.handlebars",
        "query": [{
            "collectionName": "portfolios",
            "query": {}
        }]
    },
    "404": {
        "params": {
            "title": "404: Not Found"
        },
        "page": "404.handlebars"
    }
}